ts3/__init__.py
ts3/commands.py
ts3/common.py
ts3/definitions.py
ts3/escape.py
ts3/filetransfer.py
ts3/query.py
ts3/query_builder.py
ts3/response.py
ts3/examples/__init__.py
ts3/examples/def_param.py
ts3/examples/endless_poke.py
ts3/examples/hello_bot.py
ts3/examples/viewer.py
ts3/examples/whirlpool.py
ts3-1.0.11.dist-info/METADATA
ts3-1.0.11.dist-info/RECORD
ts3-1.0.11.dist-info/WHEEL
ts3-1.0.11.dist-info/top_level.txt
