Metadata-Version: 1.1
Name: ts3
Version: 1.0.11
Summary: TS3 Server Query API
Home-page: https://github.com/benediktschmitt/py-ts3
Author: UNKNOWN
Author-email: UNKNOWN
License: License
